cosmonote/__init__.py
cosmonote/app.py
cosmonote/entrypoint.py
cosmonote/notes.py
cosmonote/utils.py
cosmonote-0.1.4.dist-info/METADATA
cosmonote-0.1.4.dist-info/WHEEL
cosmonote-0.1.4.dist-info/entry_points.txt
cosmonote-0.1.4.dist-info/RECORD
