Metadata-Version: 2.1
Name: cosmonote
Version: 0.1.4
Summary: Python client to CosmoNote.
License: Proprietary
Author: Luke Hodkinson
Author-email: furious.luke@gmail.com
Requires-Python: >=3.7,<3.11
Classifier: License :: Other/Proprietary License
Classifier: Programming Language :: Python :: 3
Classifier: Programming Language :: Python :: 3.7
Classifier: Programming Language :: Python :: 3.8
Classifier: Programming Language :: Python :: 3.9
Classifier: Programming Language :: Python :: 3.10
Requires-Dist: clickmod (>=0.1.0,<0.2.0)
Requires-Dist: clickmod-auth (>=0.1.0,<0.2.0)
Requires-Dist: python-dateutil (>=2.8.2,<3.0.0)
Requires-Dist: pytz (>=2022.6,<2023.0)
Requires-Dist: timeago (>=1.0.16,<2.0.0)
